custom_prediction_library/__init__.py
custom_prediction_library/model_creation.py
custom_prediction_library/time_series.py
custom_prediction_library/training.py
custom_prediction_library/tuning.py
custom_prediction_library/visualisation.py
custom_prediction_library-0.3.1.dist-info/METADATA
custom_prediction_library-0.3.1.dist-info/WHEEL
custom_prediction_library-0.3.1.dist-info/top_level.txt
custom_prediction_library-0.3.1.dist-info/RECORD
