Metadata-Version: 2.1
Name: custom_prediction_library
Version: 0.3.1
Summary: A custom prediction library with automated hyperparameter tuning, training utilities, exponential smoothing, and visualisation.
Author: JKEEPS
Author-email: your.email@example.com
License: MIT
Classifier: Programming Language :: Python :: 3
Classifier: License :: OSI Approved :: MIT License
Requires-Python: >=3.6
Requires-Dist: scikit-learn
Requires-Dist: optuna
Requires-Dist: bayesian-optimization
Requires-Dist: numpy
Requires-Dist: pandas
Requires-Dist: statsmodels
Requires-Dist: bokeh
